briq/__init__.py
briq/client.py
briq/config.py
briq/exceptions.py
briq/campaign/__init__.py
briq/message/__init__.py
briq/workspace/__init__.py
briq-0.1.0.dist-info/licenses/LICENSE
briq-0.1.0.dist-info/METADATA
briq-0.1.0.dist-info/WHEEL
briq-0.1.0.dist-info/top_level.txt
briq-0.1.0.dist-info/RECORD
