Metadata-Version: 2.4
Name: briq
Version: 0.1.0
Summary: Python client for the Briq messaging platform API
Home-page: https://github.com/BRIQ-BLOCK/BriqPythonSdk
Author: Briq Team
Author-email: Briq Team <info@briq.tz>
License: MIT
Project-URL: Homepage, https://github.com/briq/briq-python
Project-URL: Bug Tracker, https://github.com/briq/briq-python/issues
Classifier: Programming Language :: Python :: 3
Classifier: Programming Language :: Python :: 3.7
Classifier: Programming Language :: Python :: 3.8
Classifier: Programming Language :: Python :: 3.9
Classifier: Programming Language :: Python :: 3.10
Classifier: License :: OSI Approved :: MIT License
Classifier: Operating System :: OS Independent
Requires-Python: >=3.7
License-File: LICENSE
Requires-Dist: requests>=2.25.0
Requires-Dist: python-dotenv>=0.15.0
Dynamic: author
Dynamic: home-page
Dynamic: license-file
Dynamic: requires-python
